README.rst
setup.cfg
setup.py
connmon/__init__.py
connmon/client.py
connmon/display.py
connmon/dumper.py
connmon/frontend.py
connmon/plugin.py
connmon/server.py
connmon/stats.py
connmon.egg-info/PKG-INFO
connmon.egg-info/SOURCES.txt
connmon.egg-info/dependency_links.txt
connmon.egg-info/entry_points.txt
connmon.egg-info/not-zip-safe
connmon.egg-info/requires.txt
connmon.egg-info/top_level.txt