Metadata-Version: 1.1
Name: connmon
Version: 0.3.6
Summary: Analyze database connection usage
Home-page: http://bitbucket.org/zzzeek/connmon
Author: Mike Bayer
Author-email: mike@zzzcomputing.com
License: MIT
Keywords: SQLAlchemy
Platform: UNKNOWN
Classifier: Development Status :: 3 - Alpha
Classifier: Intended Audience :: Developers
Classifier: Programming Language :: Python
Classifier: Programming Language :: Python :: 3
Classifier: Programming Language :: Python :: Implementation :: CPython
Classifier: Programming Language :: Python :: Implementation :: PyPy
Classifier: Topic :: Database :: Front-Ends
